EarthquakesETL-1.0.12-py3.10-nspkg.pth
EarthquakesETL/eqmodel/EQBDerivedAttributes.py
EarthquakesETL/eqmodel/EQEvent.py
EarthquakesETL/eqmodel/EQInstance.py
EarthquakesETL/eqmodel/EQPgen.py
EarthquakesETL/eqmodel/__init__.py
EarthquakesETL/widgets/__init__.py
EarthquakesETL/widgets/oweqcatalogdeclustering.py
EarthquakesETL/widgets/oweqcatalogdownload.py
EarthquakesETL/widgets/oweqfeatureengineering.py
EarthquakesETL/widgets/oweqsave.py
EarthquakesETL/widgets/icons/EQCatalogCleaning.png
EarthquakesETL/widgets/icons/EQCatalogDownload.png
EarthquakesETL/widgets/icons/EQFeatureEngineering.png
EarthquakesETL/widgets/icons/EQSave.png
EarthquakesETL/widgets/icons/EarthquakesETL.svg
earthquakesetl-1.0.12.data/data/help/orange3-example/.buildinfo
earthquakesetl-1.0.12.data/data/help/orange3-example/genindex.html
earthquakesetl-1.0.12.data/data/help/orange3-example/index.html
earthquakesetl-1.0.12.data/data/help/orange3-example/objects.inv
earthquakesetl-1.0.12.data/data/help/orange3-example/search.html
earthquakesetl-1.0.12.data/data/help/orange3-example/searchindex.js
earthquakesetl-1.0.12.data/data/help/orange3-example/.doctrees/environment.pickle
earthquakesetl-1.0.12.data/data/help/orange3-example/.doctrees/index.doctree
earthquakesetl-1.0.12.data/data/help/orange3-example/.doctrees/widgets/oweqcatalogdeclustering.doctree
earthquakesetl-1.0.12.data/data/help/orange3-example/.doctrees/widgets/oweqcatalogdownload.doctree
earthquakesetl-1.0.12.data/data/help/orange3-example/.doctrees/widgets/oweqfeatureengineering.doctree
earthquakesetl-1.0.12.data/data/help/orange3-example/.doctrees/widgets/oweqsave.doctree
earthquakesetl-1.0.12.data/data/help/orange3-example/_images/ChileImage.jpg
earthquakesetl-1.0.12.data/data/help/orange3-example/_sources/index.rst.txt
earthquakesetl-1.0.12.data/data/help/orange3-example/_sources/widgets/oweqcatalogdeclustering.md.txt
earthquakesetl-1.0.12.data/data/help/orange3-example/_sources/widgets/oweqcatalogdownload.md.txt
earthquakesetl-1.0.12.dist-info/licenses/LICENSE
earthquakesetl-1.0.12.dist-info/METADATA
earthquakesetl-1.0.12.dist-info/WHEEL
earthquakesetl-1.0.12.dist-info/entry_points.txt
earthquakesetl-1.0.12.dist-info/namespace_packages.txt
earthquakesetl-1.0.12.dist-info/top_level.txt
earthquakesetl-1.0.12.dist-info/RECORD
