Metadata-Version: 2.4
Name: EarthquakesETL
Version: 1.0.12
Summary: EarthquakesETL add-on for Orange 3 data mining software.
Home-page: https://github.com/gualbe/orange-earthquakes-etl
Author: Elena Carrasco Hurtado
Author-email: ecarrascohurtado@gmail.com
License: GPL3+
Keywords: orange3 add-on,earthquakes,etl,earthquakesetl,data mining,prediction,orange,addon,models,declustering,database,catalog
Classifier: Development Status :: 4 - Beta
Classifier: Environment :: Plugins
Classifier: Programming Language :: Python
Classifier: License :: OSI Approved :: GNU General Public License v3 or later (GPLv3+)
Classifier: Operating System :: OS Independent
Classifier: Topic :: Software Development :: Libraries :: Python Modules
Classifier: Intended Audience :: Education
Classifier: Intended Audience :: Science/Research
Classifier: Intended Audience :: Developers
License-File: LICENSE
Requires-Dist: psycopg2-binary
Requires-Dist: SQLAlchemy>=2.0.40
Requires-Dist: bcrypt>=4.3.0
Requires-Dist: geopandas>=1.0.1
Requires-Dist: bs4>=0.0.2
Requires-Dist: typing>=3.7.4.3
Requires-Dist: openquake.engine>=3.23.1
Requires-Dist: fiona>=1.10.1
Requires-Dist: dataclasses>=0.6
Requires-Dist: numpy>=1.26.4
Requires-Dist: numba==0.58.1
Requires-Dist: llvmlite==0.41.1
Dynamic: author
Dynamic: author-email
Dynamic: classifier
Dynamic: description
Dynamic: description-content-type
Dynamic: home-page
Dynamic: keywords
Dynamic: license
Dynamic: license-file
Dynamic: requires-dist
Dynamic: summary
